{
    "dialogueList": [
        {
            "dialogueID": "houseWake1",
            "text": "Yawwnnnnn.",
            "timePerChar": 0.2
        },
        {
            "dialogueID": "houseWake2",
            "text": "Let's just start this day, shall we?",
            "timePerChar": 0.06
        },
        {
            "dialogueID": "houseWake3",
            "text": "I mean, what could go wrong? Something bad isn't gonna happen, right?",
            "timePerChar": 0.06
        },
        {
            "dialogueID": "houseWake4",
            "text": "*Foreshadowing*",
            "timePerChar": 0.2
        },
        {
            "dialogueID": "shocked1",
            "text": "!!!!!!!!!!!!!!!!!!!!!!!!!!!!!!!!!!!!!!!!!!!!!!!!!!!!!!!",
            "timePerChar": 0.01
        },
        {
            "dialogueID": "shocked2",
            "text": "Oh you better not be able to hurt me are you, little creep!?",
            "timePerChar": 0.04
        }
    ]
}